LICENSE
MANIFEST.in
README.md
setup.cfg
setup.py
aiomultiprocess/__init__.py
aiomultiprocess/core.py
aiomultiprocess.egg-info/PKG-INFO
aiomultiprocess.egg-info/SOURCES.txt
aiomultiprocess.egg-info/dependency_links.txt
aiomultiprocess.egg-info/top_level.txt
aiomultiprocess/tests/__init__.py
aiomultiprocess/tests/__main__.py
aiomultiprocess/tests/base.py
aiomultiprocess/tests/core.py
aiomultiprocess/tests/perf.py