Metadata-Version: 2.1
Name: aiomultiprocess
Version: 0.6.1
Summary: asyncio version of the standard multiprocessing module
Home-page: https://github.com/jreese/aiomultiprocess
Author: John Reese
Author-email: john@noswap.com
License: MIT
Platform: UNKNOWN
Classifier: Development Status :: 4 - Beta
Classifier: Framework :: AsyncIO
Classifier: Intended Audience :: Developers
Classifier: License :: OSI Approved :: MIT License
Classifier: Programming Language :: Python
Classifier: Programming Language :: Python :: 3
Classifier: Programming Language :: Python :: 3.6
Classifier: Programming Language :: Python :: 3.7
Classifier: Topic :: Software Development :: Libraries
Requires-Python: >=3.6
